rayvision_log/__init__.py
rayvision_log/core.py
rayvision_log/logging.yaml
rayvision_log/tests/__init__.py
rayvision_log/tests/test_core.py
rayvision_log-1.2.4.dist-info/LICENSE
rayvision_log-1.2.4.dist-info/METADATA
rayvision_log-1.2.4.dist-info/WHEEL
rayvision_log-1.2.4.dist-info/top_level.txt
rayvision_log-1.2.4.dist-info/RECORD
