Metadata-Version: 2.1
Name: rayvision-log
Version: 1.2.4
Summary: A Python-based API for Using Renderbus cloud rendering service.
Home-page: https://github.com/renderbus/rayvision_log
Author: Shenzhen Rayvision Technology Co., Ltd
Author-email: developer@rayvision.com
Classifier: Programming Language :: Python
Classifier: Programming Language :: Python :: 2
Classifier: Programming Language :: Python :: 3
License-File: LICENSE
Requires-Dist: appdirs ==1.4.3
Requires-Dist: concurrent-log-handler ==0.9.16
Requires-Dist: pyyaml >=5.1.2
Requires-Dist: configparser ==4.0.2
